{
  "swagger": "2.0",
  "info": {
    "title": "Family Track API",
    "description": "Family Track API",
    "version": "1.0.0"
  },
  "host": "cse341-familytrack.onrender.com",
  "basePath": "/",
  "schemes": [
    "https"
  ],
  "paths": {
    "/": {
      "get": {
        "tags": [
          "Hello World"
        ],
        "description": "",
        "responses": {
          "200": {
            "description": "OK"
          }
        }
      }
    },
    "/stake/": {
      "get": {
        "tags": [
          "Stake"
        ],
        "description": "",
        "produces": [
          "application/json"
        ],
        "responses": {
          "200": {
            "description": "OK"
          },
          "500": {
            "description": "Internal Server Error"
          }
        }
      },
      "post": {
        "tags": [
          "Stake"
        ],
        "description": "",
        "parameters": [
          {
            "name": "body",
            "in": "body",
            "schema": {
              "type": "object",
              "properties": {
                "country": {
                  "example": "any"
                },
                "name": {
                  "example": "any"
                }
              }
            }
          }
        ],
        "responses": {
          "201": {
            "description": "Created"
          },
          "422": {
            "description": "Unprocessable Entity"
          },
          "500": {
            "description": "Internal Server Error"
          }
        }
      }
    },
    "/stake/{id}": {
      "get": {
        "tags": [
          "Stake"
        ],
        "description": "",
        "produces": [
          "application/json"
        ],
        "parameters": [
          {
            "name": "id",
            "in": "path",
            "required": true,
            "type": "string"
          }
        ],
        "responses": {
          "200": {
            "description": "OK"
          },
          "404": {
            "description": "Not Found"
          },
          "500": {
            "description": "Internal Server Error"
          }
        }
      },
      "put": {
        "tags": [
          "Stake"
        ],
        "description": "",
        "parameters": [
          {
            "name": "id",
            "in": "path",
            "required": true,
            "type": "string"
          },
          {
            "name": "body",
            "in": "body",
            "schema": {
              "type": "object",
              "properties": {
                "country": {
                  "example": "any"
                },
                "name": {
                  "example": "any"
                }
              }
            }
          }
        ],
        "responses": {
          "204": {
            "description": "No Content"
          },
          "422": {
            "description": "Unprocessable Entity"
          },
          "500": {
            "description": "Internal Server Error"
          }
        }
      },
      "delete": {
        "tags": [
          "Stake"
        ],
        "description": "",
        "parameters": [
          {
            "name": "id",
            "in": "path",
            "required": true,
            "type": "string"
          }
        ],
        "responses": {
          "204": {
            "description": "No Content"
          },
          "500": {
            "description": "Internal Server Error"
          }
        }
      }
    },
    "/ward/": {
      "get": {
        "tags": [
          "Ward"
        ],
        "description": "",
        "produces": [
          "application/json"
        ],
        "responses": {
          "200": {
            "description": "OK"
          },
          "500": {
            "description": "Internal Server Error"
          }
        }
      },
      "post": {
        "tags": [
          "Ward"
        ],
        "description": "",
        "parameters": [
          {
            "name": "body",
            "in": "body",
            "schema": {
              "type": "object",
              "properties": {
                "name": {
                  "example": "any"
                },
                "stakeId": {
                  "example": "any"
                }
              }
            }
          }
        ],
        "responses": {
          "201": {
            "description": "Created"
          },
          "422": {
            "description": "Unprocessable Entity"
          },
          "500": {
            "description": "Internal Server Error"
          }
        }
      }
    },
    "/ward/{id}": {
      "get": {
        "tags": [
          "Ward"
        ],
        "description": "",
        "produces": [
          "application/json"
        ],
        "parameters": [
          {
            "name": "id",
            "in": "path",
            "required": true,
            "type": "string"
          }
        ],
        "responses": {
          "200": {
            "description": "OK"
          },
          "404": {
            "description": "Not Found"
          },
          "500": {
            "description": "Internal Server Error"
          }
        }
      },
      "put": {
        "tags": [
          "Ward"
        ],
        "description": "",
        "parameters": [
          {
            "name": "id",
            "in": "path",
            "required": true,
            "type": "string"
          },
          {
            "name": "body",
            "in": "body",
            "schema": {
              "type": "object",
              "properties": {
                "name": {
                  "example": "any"
                },
                "stakeId": {
                  "example": "any"
                }
              }
            }
          }
        ],
        "responses": {
          "204": {
            "description": "No Content"
          },
          "422": {
            "description": "Unprocessable Entity"
          },
          "500": {
            "description": "Internal Server Error"
          }
        }
      },
      "delete": {
        "tags": [
          "Ward"
        ],
        "description": "",
        "parameters": [
          {
            "name": "id",
            "in": "path",
            "required": true,
            "type": "string"
          }
        ],
        "responses": {
          "204": {
            "description": "No Content"
          },
          "500": {
            "description": "Internal Server Error"
          }
        }
      }
    },
    "/member/": {
      "get": {
        "tags": [
          "Member"
        ],
        "description": "",
        "produces": [
          "application/json"
        ],
        "responses": {
          "200": {
            "description": "OK"
          },
          "500": {
            "description": "Internal Server Error"
          }
        }
      },
      "post": {
        "tags": [
          "Member"
        ],
        "description": "",
        "parameters": [
          {
            "name": "body",
            "in": "body",
            "schema": {
              "type": "object",
              "properties": {
                "name": {
                  "example": "any"
                },
                "birthday": {
                  "example": "any"
                },
                "email": {
                  "example": "any"
                },
                "wardId": {
                  "example": "any"
                }
              }
            }
          }
        ],
        "responses": {
          "201": {
            "description": "Created"
          },
          "422": {
            "description": "Unprocessable Entity"
          },
          "500": {
            "description": "Internal Server Error"
          }
        }
      }
    },
    "/member/{id}": {
      "get": {
        "tags": [
          "Member"
        ],
        "description": "",
        "produces": [
          "application/json"
        ],
        "parameters": [
          {
            "name": "id",
            "in": "path",
            "required": true,
            "type": "string"
          }
        ],
        "responses": {
          "200": {
            "description": "OK"
          },
          "404": {
            "description": "Not Found"
          },
          "500": {
            "description": "Internal Server Error"
          }
        }
      },
      "put": {
        "tags": [
          "Member"
        ],
        "description": "",
        "parameters": [
          {
            "name": "id",
            "in": "path",
            "required": true,
            "type": "string"
          },
          {
            "name": "body",
            "in": "body",
            "schema": {
              "type": "object",
              "properties": {
                "name": {
                  "example": "any"
                },
                "birthday": {
                  "example": "any"
                },
                "email": {
                  "example": "any"
                },
                "wardId": {
                  "example": "any"
                }
              }
            }
          }
        ],
        "responses": {
          "204": {
            "description": "No Content"
          },
          "422": {
            "description": "Unprocessable Entity"
          },
          "500": {
            "description": "Internal Server Error"
          }
        }
      },
      "delete": {
        "tags": [
          "Member"
        ],
        "description": "",
        "parameters": [
          {
            "name": "id",
            "in": "path",
            "required": true,
            "type": "string"
          }
        ],
        "responses": {
          "204": {
            "description": "No Content"
          },
          "500": {
            "description": "Internal Server Error"
          }
        }
      }
    },
    "/ancestor/": {
      "get": {
        "tags": [
          "Ancestor"
        ],
        "description": "",
        "produces": [
          "application/json"
        ],
        "responses": {
          "200": {
            "description": "OK"
          },
          "500": {
            "description": "Internal Server Error"
          }
        }
      },
      "post": {
        "tags": [
          "Ancestor"
        ],
        "description": "",
        "parameters": [
          {
            "name": "body",
            "in": "body",
            "schema": {
              "type": "object",
              "properties": {
                "firstName": {
                  "example": "any"
                },
                "lastName": {
                  "example": "any"
                },
                "birthday": {
                  "example": "any"
                },
                "deathdate": {
                  "example": "any"
                },
                "baptisms": {
                  "example": "any"
                },
                "confirmation": {
                  "example": "any"
                },
                "initiatory": {
                  "example": "any"
                },
                "endowment": {
                  "example": "any"
                },
                "sealingSpouse": {
                  "example": "any"
                },
                "sealingParents": {
                  "example": "any"
                },
                "ordinanceCard": {
                  "example": "any"
                },
                "memberId": {
                  "example": "any"
                },
                "mimetypeFile": {
                  "example": "any"
                }
              }
            }
          }
        ],
        "responses": {
          "201": {
            "description": "Created"
          },
          "422": {
            "description": "Unprocessable Entity"
          },
          "500": {
            "description": "Internal Server Error"
          }
        }
      }
    },
    "/ancestor/{id}": {
      "get": {
        "tags": [
          "Ancestor"
        ],
        "description": "",
        "produces": [
          "application/json"
        ],
        "parameters": [
          {
            "name": "id",
            "in": "path",
            "required": true,
            "type": "string"
          }
        ],
        "responses": {
          "200": {
            "description": "OK"
          },
          "404": {
            "description": "Not Found"
          },
          "500": {
            "description": "Internal Server Error"
          }
        }
      },
      "put": {
        "tags": [
          "Ancestor"
        ],
        "description": "",
        "parameters": [
          {
            "name": "id",
            "in": "path",
            "required": true,
            "type": "string"
          },
          {
            "name": "body",
            "in": "body",
            "schema": {
              "type": "object",
              "properties": {
                "firstName": {
                  "example": "any"
                },
                "lastName": {
                  "example": "any"
                },
                "birthday": {
                  "example": "any"
                },
                "deathdate": {
                  "example": "any"
                },
                "baptisms": {
                  "example": "any"
                },
                "confirmation": {
                  "example": "any"
                },
                "initiatory": {
                  "example": "any"
                },
                "endowment": {
                  "example": "any"
                },
                "sealingSpouse": {
                  "example": "any"
                },
                "sealingParents": {
                  "example": "any"
                },
                "ordinanceCard": {
                  "example": "any"
                },
                "memberId": {
                  "example": "any"
                },
                "mimetypeFile": {
                  "example": "any"
                }
              }
            }
          }
        ],
        "responses": {
          "204": {
            "description": "No Content"
          },
          "422": {
            "description": "Unprocessable Entity"
          },
          "500": {
            "description": "Internal Server Error"
          }
        }
      },
      "delete": {
        "tags": [
          "Ancestor"
        ],
        "description": "",
        "parameters": [
          {
            "name": "id",
            "in": "path",
            "required": true,
            "type": "string"
          }
        ],
        "responses": {
          "204": {
            "description": "No Content"
          },
          "500": {
            "description": "Internal Server Error"
          }
        }
      }
    }
  }
}